julax/__init__.py
julax/base.py
julax/utils.py
julax/experiment/__init__.py
julax/experiment/experiment.py
julax/experiment/observers.py
julax/experiment/run.py
julax/layers/__init__.py
julax/layers/base.py
julax/layers/commons.py
julax/layers/connectors.py
julax/layers/core.py
julax/layers/einops.py
julax/layers/pprint.py
julax-0.0.6.dist-info/METADATA
julax-0.0.6.dist-info/WHEEL
julax-0.0.6.dist-info/entry_points.txt
julax-0.0.6.dist-info/licenses/LICENSE
julax-0.0.6.dist-info/RECORD
